[
	{
		"enabled": true,
		"updateUrl": null,
		"md5Url": null,
		"url": null,
		"originalMd5": null,
		"installDate": 1592371971518,
		"name": "Theme Plus",
		"sections": [
			{
				"code": "/* Colab Theme+ */\n/* benjavicente */\n/* https://www.jsdelivr.com/?docs=gh */\n@import url(https://cdn.jsdelivr.net/npm/firacode@5.2.0/distr/fira_code.css);\n\n\n/* ╒══════════════╕ */\n/* │    Themes    │ */\n/* ╘══════════════╛ */\n/* Dark Theme */\nhtml[theme=dark] {\n    --colab-primary-surface-color: #29292a;\n    --colab-secondary-surface-color: #444447;\n    --colab-primary-text-color: #fff;\n    --colab-toolbar-button-color: #aaa;\n    --colab-icon-color: #aaa;\n    --colab-border-color: #5f5f5f;\n\n    --font-weight: 400;\n    --code-cell-background: #00010f;\n    --code-selected-active: #63b4ff38;\n    --code-selected-inactive: #c5e4fe24;\n\n    --code-main: #f8f8f8;\n    --code-function: #e8e8a8;\n    --code-class: #55ddcb;\n    --code-string: #feb796;\n    --code-number: #a4d988;\n    --code-comment: #6ab056;\n    --code-punctuation: #e0e0e0;\n    --code-keywords-1: #c586c0;\n    --code-keywords-2: #76c1ff;\n    --code-bool: #4799dd;\n    --code-arguments: #9cdcfe;\n}\n\n\n/* Light Theme */\nhtml[theme=light] {\n\n    --colab-primary-surface-color: #e5e5e5;\n    --colab-secondary-surface-color: #cfcfcf;\n    --colab-primary-text-color: #000;\n    --colab-toolbar-button-color: #000;\n    --colab-icon-color: #000;\n    --colab-border-color: #999;\n\n    --font-weight: 600;\n    --code-cell-background: #f9f9f9;\n    --code-selected-active: #63b4ff4a;\n    --code-selected-inactive: #63abef24;\n\n    --code-main: #000;\n    --code-function: #7d7d00;\n    --code-class: #267f99;\n    --code-string: #b03800;\n    --code-number: #009e65;\n    --code-comment: #008000;\n    --code-keywords-1: #b200df;\n    --code-keywords-2: #0000ff;\n    --code-arguments: #0053aa;\n}\n\n\n/* ╒═════════════╕ */\n/* │    SetUp    │ */\n/* ╘═════════════╛ */\nhtml[theme=dark] {\n    --mtk1: var(--code-main);\n    --mtk4: var(--code-arguments);\n    --mtk5: var(--code-string);\n    --mtk6: var(--code-number);\n    --mtk8: var(--code-comment);\n    --mtk9: var(--code-bool);\n    --mtk12: var(--code-punctuation);\n    --mtk14: var(--code-class);\n    --mtk15: var(--code-function);\n    --mtk18: var(--code-keywords-2);\n    --mtk19: var(--code-keywords-1);\n}\n\nhtml[theme=light] {\n    --mtk1: var(--code-main);\n    --mtk6: var(--code-keywords-2);\n    --mtk8: var(--code-comment);\n    --mtk11: var(--code-number);\n    --mtk13: var(--code-class);\n    --mtk14: var(--code-function);\n    --mtk15: var(--code-arguments);\n    --mtk18: var(--code-keywords-1);\n    --mtk26: var(--code-string);\n}\n\n/* Font */\n.code,\n.monaco-editor .view-lines,\n.inputarea,\n.monaco-tokenized-source {\n    font-family: 'Fira Code', monospace !important;\n    font-weight: var(--font-weight) !important;\n}\n\n@supports (font-variation-settings: normal) {\n    .code,\n    .monaco-editor .view-lines,\n    .inputarea,\n    .monaco-tokenized-source {\n        font-family: 'Fira Code VF', monospace !important;\n    }\n}\n\n/* Focus */\n.monaco-editor .focused .selected-text {\n    background-color: var(--code-selected-active)\n}\n.view-overlays .selected-text {\n    background-color: var(--code-selected-inactive)\n}\n\n/* Background */\n.codecell-input-output .margin-view-overlays,\n.monaco-editor-background {\n    background: var(--code-cell-background)\n}\n\n/* Code classes */\n.monaco-editor .mtk0 {\n    color: var(--mtk0)\n}\n.monaco-editor .mtk1 {\n    color: var(--mtk1)\n}\n.monaco-editor .mtk2 {\n    color: var(--mtk2)\n}\n.monaco-editor .mtk3 {\n    color: var(--mtk3)\n}\n.monaco-editor .mtk4 {\n    color: var(--mtk4)\n}\n.monaco-editor .mtk5 {\n    color: var(--mtk5)\n}\n.monaco-editor .mtk6 {\n    color: var(--mtk6)\n}\n.monaco-editor .mtk7 {\n    color: var(--mtk7)\n}\n.monaco-editor .mtk8 {\n    color: var(--mtk8)\n}\n.monaco-editor .mtk9 {\n    color: var(--mtk9)\n}\n.monaco-editor .mtk10 {\n    color: var(--mtk10)\n}\n.monaco-editor .mtk11 {\n    color: var(--mtk11)\n}\n.monaco-editor .mtk12 {\n    color: var(--mtk12)\n}\n.monaco-editor .mtk13 {\n    color: var(--mtk13)\n}\n.monaco-editor .mtk14 {\n    color: var(--mtk14)\n}\n.monaco-editor .mtk15 {\n    color: var(--mtk15)\n}\n.monaco-editor .mtk16 {\n    color: var(--mtk16)\n}\n.monaco-editor .mtk17 {\n    color: var(--mtk17)\n}\n.monaco-editor .mtk18 {\n    color: var(--mtk18)\n}\n.monaco-editor .mtk19 {\n    color: var(--mtk19)\n}\n.monaco-editor .mtk20 {\n    color: var(--mtk20)\n}\n.monaco-editor .mtk21 {\n    color: var(--mtk21)\n}\n.monaco-editor .mtk22 {\n    color: var(--mtk22)\n}\n.monaco-editor .mtk23 {\n    color: var(--mtk23)\n}\n.monaco-editor .mtk24 {\n    color: var(--mtk24)\n}\n.monaco-editor .mtk25 {\n    color: var(--mtk25)\n}\n.monaco-editor .mtk26 {\n    color: var(--mtk26)\n}",
				"urlPrefixes": [
					"https://colab.research.google.com/"
				]
			}
		],
		"updateDate": 1592372021459,
		"_id": "abd9dde0-997f-4108-819a-72a58c6f28cb",
		"_rev": 1592372021459,
		"id": 1
	}
]
